Metadata-Version: 2.1
Name: Mensajes-Juanpa2907
Version: 6.0
Summary: Un paquete para saludar y despedir
Home-page: https://www.juanpa.dev
Author: Juan Pablo Ruiz
Author-email: juanpa.ruiz@juanp.dev
Classifier: Environment :: Console
Classifier: Intended Audience :: Developers
Classifier: License :: OSI Approved :: MIT License
Classifier: Operating System :: OS Independent
Classifier: Programming Language :: Python
Classifier: Programming Language :: Python :: 3.10
Classifier: Topic :: Utilities
License-File: LICENSE
Requires-Dist: numpy >=1.24.3
